{
  "data": {
    "article": {},
    "attachments": {
      "media_keys": [
        "3_2063871826674253825",
        "3_2063871826670100480"
      ]
    },
    "author_id": "1863233896403628033",
    "conversation_id": "2063871843057246662",
    "created_at": "2026-06-08T06:32:46.000Z",
    "edit_controls": {
      "editable_until": "2026-06-08T07:32:46.000Z",
      "edits_remaining": 5,
      "is_edit_eligible": true
    },
    "edit_history_tweet_ids": [
      "2063871843057246662"
    ],
    "entities": {
      "urls": [
        {
          "display_url": "pic.x.com/RUIbwNp7cK",
          "end": 69,
          "expanded_url": "https://x.com/dontweepalone/status/2063871843057246662/photo/1",
          "media_key": "3_2063871826674253825",
          "start": 46,
          "url": "https://t.co/RUIbwNp7cK"
        },
        {
          "display_url": "pic.x.com/RUIbwNp7cK",
          "end": 69,
          "expanded_url": "https://x.com/dontweepalone/status/2063871843057246662/photo/1",
          "media_key": "3_2063871826670100480",
          "start": 46,
          "url": "https://t.co/RUIbwNp7cK"
        }
      ]
    },
    "geo": {},
    "id": "2063871843057246662",
    "lang": "zh",
    "note_tweet": {
      "entities": {}
    },
    "possibly_sensitive": false,
    "public_metrics": {
      "bookmark_count": 0,
      "impression_count": 0,
      "like_count": 0,
      "quote_count": 0,
      "reply_count": 0,
      "retweet_count": 0
    },
    "reply_settings": "everyone",
    "text": "我会成为我自己的母亲，并在自己对自己的无限的爱里安心地死去。\n（半年前写的了，貌似没发过。 https://t.co/RUIbwNp7cK"
  },
  "includes": {
    "media": [
      {
        "height": 2048,
        "media_key": "3_2063871826674253825",
        "public_metrics": {},
        "type": "photo",
        "url": "https://pbs.twimg.com/media/HKRYfdLbAAEQAeO.jpg",
        "width": 942
      },
      {
        "height": 2048,
        "media_key": "3_2063871826670100480",
        "public_metrics": {},
        "type": "photo",
        "url": "https://pbs.twimg.com/media/HKRYfdKboAADhtd.jpg",
        "width": 942
      }
    ],
    "tweets": [
      {
        "article": {},
        "attachments": {
          "media_keys": [
            "3_2063871826674253825",
            "3_2063871826670100480"
          ]
        },
        "author_id": "1863233896403628033",
        "conversation_id": "2063871843057246662",
        "created_at": "2026-06-08T06:32:46.000Z",
        "edit_controls": {
          "editable_until": "2026-06-08T07:32:46.000Z",
          "edits_remaining": 5,
          "is_edit_eligible": true
        },
        "edit_history_tweet_ids": [
          "2063871843057246662"
        ],
        "entities": {
          "urls": [
            {
              "display_url": "pic.x.com/RUIbwNp7cK",
              "end": 69,
              "expanded_url": "https://x.com/dontweepalone/status/2063871843057246662/photo/1",
              "media_key": "3_2063871826674253825",
              "start": 46,
              "url": "https://t.co/RUIbwNp7cK"
            },
            {
              "display_url": "pic.x.com/RUIbwNp7cK",
              "end": 69,
              "expanded_url": "https://x.com/dontweepalone/status/2063871843057246662/photo/1",
              "media_key": "3_2063871826670100480",
              "start": 46,
              "url": "https://t.co/RUIbwNp7cK"
            }
          ]
        },
        "geo": {},
        "id": "2063871843057246662",
        "lang": "zh",
        "note_tweet": {
          "entities": {}
        },
        "possibly_sensitive": false,
        "public_metrics": {
          "bookmark_count": 0,
          "impression_count": 0,
          "like_count": 0,
          "quote_count": 0,
          "reply_count": 0,
          "retweet_count": 0
        },
        "reply_settings": "everyone",
        "text": "我会成为我自己的母亲，并在自己对自己的无限的爱里安心地死去。\n（半年前写的了，貌似没发过。 https://t.co/RUIbwNp7cK"
      }
    ],
    "users": [
      {
        "created_at": "2024-12-01T14:49:35.000Z",
        "description": "@mnweeper二世\nINFP｜4w5｜06｜agender(they)｜lgbtqa+全友好｜acearo｜精神障碍｜shtwt｜欢迎互fo^_^\nWelcome to my funeral.",
        "entities": {
          "description": {
            "mentions": [
              {
                "end": 9,
                "start": 0,
                "username": "mnweeper"
              }
            ]
          }
        },
        "id": "1863233896403628033",
        "name": "Mnweeper_",
        "profile_image_url": "https://pbs.twimg.com/profile_images/2063267130548908032/lNkisJk0_normal.jpg",
        "protected": false,
        "public_metrics": {
          "followers_count": 203,
          "following_count": 135,
          "like_count": 923,
          "listed_count": 2,
          "media_count": 16,
          "tweet_count": 172
        },
        "username": "dontweepalone",
        "verified": false
      }
    ]
  }
}